[
  {
    "id": "anne_autriche",
    "name": "Anne Autriche",
    "subtitle": "",
    "type": "Personnage",
    "power": 70,
    "charisma": 95,
    "love": 85,
    "intelligence": 90,
    "img": "/personnages/anne_autriche.jpg"
  },
  {
    "id": "colbert",
    "name": "Colbert",
    "subtitle": "",
    "type": "Personnage",
    "power": 70,
    "charisma": 95,
    "love": 85,
    "intelligence": 90,
    "img": "/personnages/colbert.jpg"
  },
  {
    "id": "courtisane",
    "name": "Courtisane",
    "subtitle": "",
    "type": "Courtisane",
    "power": 70,
    "charisma": 95,
    "love": 85,
    "intelligence": 90,
    "img": "/personnages/courtisane.jpg"
  },
  {
    "id": "dame_cour",
    "name": "Dame Cour",
    "subtitle": "",
    "type": "Dame de cour",
    "power": 70,
    "charisma": 95,
    "love": 85,
    "intelligence": 90,
    "img": "/personnages/dame_cour.jpg"
  },
  {
    "id": "danseuse",
    "name": "Danseuse",
    "subtitle": "",
    "type": "Personnage",
    "power": 70,
    "charisma": 95,
    "love": 85,
    "intelligence": 90,
    "img": "/personnages/danseuse.jpg"
  },
  {
    "id": "duc_beaufort",
    "name": "Duc Beaufort",
    "subtitle": "",
    "type": "Personnage",
    "power": 70,
    "charisma": 95,
    "love": 85,
    "intelligence": 90,
    "img": "/personnages/duc_beaufort.jpg"
  },
  {
    "id": "enfant_roi",
    "name": "Enfant Roi",
    "subtitle": "",
    "type": "Royauté",
    "power": 70,
    "charisma": 95,
    "love": 85,
    "intelligence": 90,
    "img": "/personnages/enfant_roi.jpg"
  },
  {
    "id": "eveque",
    "name": "Eveque",
    "subtitle": "",
    "type": "Personnage",
    "power": 70,
    "charisma": 95,
    "love": 85,
    "intelligence": 90,
    "img": "/personnages/eveque.jpg"
  },
  {
    "id": "femme_chambre",
    "name": "Femme Chambre",
    "subtitle": "",
    "type": "Personnage",
    "power": 70,
    "charisma": 95,
    "love": 85,
    "intelligence": 90,
    "img": "/personnages/femme_chambre.jpg"
  },
  {
    "id": "femme_peuple",
    "name": "Femme Peuple",
    "subtitle": "",
    "type": "Personnage",
    "power": 70,
    "charisma": 95,
    "love": 85,
    "intelligence": 90,
    "img": "/personnages/femme_peuple.jpg"
  },
  {
    "id": "isabelle",
    "name": "Isabelle",
    "subtitle": "",
    "type": "Personnage",
    "power": 70,
    "charisma": 95,
    "love": 85,
    "intelligence": 90,
    "img": "/personnages/isabelle.jpg"
  },
  {
    "id": "la_voisin",
    "name": "La Voisin",
    "subtitle": "",
    "type": "Personnage",
    "power": 70,
    "charisma": 95,
    "love": 85,
    "intelligence": 90,
    "img": "/personnages/la_voisin.jpg"
  },
  {
    "id": "louis_xiv",
    "name": "Louis Xiv",
    "subtitle": "Le Roi Soleil",
    "type": "Royauté",
    "power": 95,
    "charisma": 100,
    "love": 85,
    "intelligence": 90,
    "img": "/personnages/louis_xiv.jpg"
  },
  {
    "id": "louis_xivold",
    "name": "Louis Xivold",
    "subtitle": "Le Roi Soleil",
    "type": "Royauté",
    "power": 95,
    "charisma": 100,
    "love": 85,
    "intelligence": 90,
    "img": "/personnages/louis_xivold.jpg"
  },
  {
    "id": "madame_montespan",
    "name": "Madame Montespan",
    "subtitle": "",
    "type": "Personnage",
    "power": 70,
    "charisma": 95,
    "love": 85,
    "intelligence": 90,
    "img": "/personnages/madame_montespan.jpg"
  },
  {
    "id": "marie_mancini",
    "name": "Marie Mancini",
    "subtitle": "Premier Amour",
    "type": "Personnage",
    "power": 70,
    "charisma": 95,
    "love": 85,
    "intelligence": 90,
    "img": "/personnages/marie_mancini.jpg"
  },
  {
    "id": "mazarin",
    "name": "Mazarin",
    "subtitle": "",
    "type": "Personnage",
    "power": 70,
    "charisma": 95,
    "love": 85,
    "intelligence": 90,
    "img": "/personnages/mazarin.jpg"
  },
  {
    "id": "medecin",
    "name": "Medecin",
    "subtitle": "",
    "type": "Personnage",
    "power": 70,
    "charisma": 95,
    "love": 85,
    "intelligence": 90,
    "img": "/personnages/medecin.jpg"
  },
  {
    "id": "mlle_lisieux",
    "name": "Mlle Lisieux",
    "subtitle": "",
    "type": "Personnage",
    "power": 70,
    "charisma": 95,
    "love": 85,
    "intelligence": 90,
    "img": "/personnages/mlle_lisieux.jpg"
  },
  {
    "id": "mme_maintenon",
    "name": "Mme Maintenon",
    "subtitle": "",
    "type": "Personnage",
    "power": 70,
    "charisma": 95,
    "love": 85,
    "intelligence": 90,
    "img": "/personnages/mme_maintenon.jpg"
  },
  {
    "id": "moliere",
    "name": "Moliere",
    "subtitle": "",
    "type": "Personnage",
    "power": 70,
    "charisma": 95,
    "love": 85,
    "intelligence": 90,
    "img": "/personnages/moliere.jpg"
  },
  {
    "id": "ninon_enclos",
    "name": "Ninon Enclos",
    "subtitle": "",
    "type": "Personnage",
    "power": 70,
    "charisma": 95,
    "love": 85,
    "intelligence": 90,
    "img": "/personnages/ninon_enclos.jpg"
  },
  {
    "id": "paul_scarron",
    "name": "Paul Scarron",
    "subtitle": "",
    "type": "Personnage",
    "power": 70,
    "charisma": 95,
    "love": 85,
    "intelligence": 90,
    "img": "/personnages/paul_scarron.jpg"
  },
  {
    "id": "philippe_orleans",
    "name": "Philippe Orleans",
    "subtitle": "",
    "type": "Personnage",
    "power": 70,
    "charisma": 95,
    "love": 85,
    "intelligence": 90,
    "img": "/personnages/philippe_orleans.jpg"
  },
  {
    "id": "soldat",
    "name": "Soldat",
    "subtitle": "",
    "type": "Personnage",
    "power": 70,
    "charisma": 95,
    "love": 85,
    "intelligence": 90,
    "img": "/personnages/soldat.jpg"
  }
]